<?xml version="1.0" encoding="utf-8"?>
<SoundBanksInfo Platform="Mac" BasePlatform="Mac" SchemaVersion="11" SoundbankVersion="134">
	<RootPaths>
		<ProjectRoot>C:\Users\rh_mk\Desktop\RPGProject_1\RPG Project Wwise\RPG Project 1\</ProjectRoot>
		<SourceFilesRoot>C:\Users\rh_mk\Desktop\RPGProject_1\RPG Project Wwise\RPG Project 1\.cache\Mac\</SourceFilesRoot>
		<SoundBanksRoot>C:\Users\rh_mk\Desktop\RPGProject_1\RPG Project Wwise\RPG Project 1\GeneratedSoundBanks\Mac\</SoundBanksRoot>
		<ExternalSourcesInputFile></ExternalSourcesInputFile>
		<ExternalSourcesOutputRoot>C:\Users\rh_mk\Desktop\RPGProject_1\RPG Project Wwise\RPG Project 1\GeneratedSoundBanks\Mac</ExternalSourcesOutputRoot>
	</RootPaths>
	<DialogueEvents/>
	<StreamedFiles/>
	<MediaFilesNotInAnyBank/>
	<SoundBanks>
		<SoundBank Id="1355168291" Language="SFX">
			<ObjectPath>Init</ObjectPath>
			<ShortName>Init</ShortName>
			<Path>Init.bnk</Path>
		</SoundBank>
		<SoundBank Id="3161908922" Language="SFX">
			<ObjectPath>\SoundBanks\Default Work Unit\Main</ObjectPath>
			<ShortName>Main</ShortName>
			<Path>Main.bnk</Path>
			<IncludedEvents>
				<Event Id="3991942870" Name="Music" ObjectPath="\Events\Default Work Unit\Music" DurationType="Infinite"/>
			</IncludedEvents>
			<IncludedMemoryFiles>
				<File Id="149409371" Language="SFX">
					<ShortName>AquaLungers_MenuTheme_Intro.wav</ShortName>
					<Path>SFX\AquaLungers_MenuTheme_Intro_D79FB2B7.wem</Path>
				</File>
				<File Id="174969013" Language="SFX">
					<ShortName>AquaLungers_MenuTheme_Main.wav</ShortName>
					<Path>SFX\AquaLungers_MenuTheme_Main_D79FB2B7.wem</Path>
				</File>
				<File Id="445660192" Language="SFX">
					<ShortName>AquaLungers_MenuTheme_Bridge.wav</ShortName>
					<Path>SFX\AquaLungers_MenuTheme_Bridge_D79FB2B7.wem</Path>
				</File>
			</IncludedMemoryFiles>
		</SoundBank>
	</SoundBanks>
</SoundBanksInfo>
